[
    {
        "1": "2",
        "0": "1",
        "['Dry laundries with sunlight and natural breezes'\"": "['Do laundry with a full load'\"",
        " '\"利用日光與自然風乾衣'\"": " '\"儲滿一機衣物才開動洗衣機'\"",
        " '\"利用日光与自然风干衣'\"]\"": " '\"储满一机衣物才开动洗衣机'\"]\""
    },
    {
        "1": "3",
        "0": "2",
        "['Dry laundries with sunlight and natural breezes'\"": "['Leave room doors and windows open for better ventilation'\"",
        " '\"利用日光與自然風乾衣'\"": " '\"打開房門窗，增加空氣流動'\"",
        " '\"利用日光与自然风干衣'\"]\"": " '\"打开房门窗， 增加空气流动'\"]\""
    },
    {
        "1": "4",
        "0": "3",
        "['Dry laundries with sunlight and natural breezes'\"": "['Use other methods to substitute using air-conditioning/heater'\"",
        " '\"利用日光與自然風乾衣'\"": " '\"以其他方法代替開冷氣/暖氣'\"",
        " '\"利用日光与自然风干衣'\"]\"": " '\"以其他方法代替开冷气/暖气'\"]\""
    },
    {
        "1": "5",
        "0": "4",
        "['Dry laundries with sunlight and natural breezes'\"": "['Use the fan with air-conditioning'\"",
        " '\"利用日光與自然風乾衣'\"": " '\"開冷氣時配合使用風扇'\"",
        " '\"利用日光与自然风干衣'\"]\"": " '\"冷气时配合使用风扇'\"]\""
    },
    {
        "1": "6",
        "0": "5",
        "['Dry laundries with sunlight and natural breezes'\"": "['Finish showering in 10 minutes'\"",
        " '\"利用日光與自然風乾衣'\"": " '\"淋浴不超過10分鐘'\"",
        " '\"利用日光与自然风干衣'\"]\"": " '\"淋浴不超过10分钟'\"]\""
    },
    {
        "1": "7",
        "0": "6",
        "['Dry laundries with sunlight and natural breezes'\"": "['Switch off or unplug idle electronic appliances'\"",
        " '\"利用日光與自然風乾衣'\"": " '\"將無用的電器電源關掉或將其插頭拔除'\"",
        " '\"利用日光与自然风干衣'\"]\"": " '\"将无用的电器电源关掉或将其插头拔除'\"]\""
    },
    {
        "1": "8",
        "0": "7",
        "['Dry laundries with sunlight and natural breezes'\"": "['Use the stairs instead of escalators or lifts'\"",
        " '\"利用日光與自然風乾衣'\"": " '\"使用樓梯代替電梯或扶手電梯'\"",
        " '\"利用日光与自然风干衣'\"]\"": " '\"使用楼梯代替电梯或扶手电梯'\"]\""
    },
    {
        "1": "9",
        "0": "8",
        "['Dry laundries with sunlight and natural breezes'\"": "['Go for a walk/do outdoor activities'\"",
        " '\"利用日光與自然風乾衣'\"": " '\"到戶外活動一下/散散步'\"",
        " '\"利用日光与自然风干衣'\"]\"": " '\"到户外活动一下/散散步'\"]\""
    },
    {
        "1": "10",
        "0": "9",
        "['Dry laundries with sunlight and natural breezes'\"": "['Share energy saving tips with families and neighbours'\"",
        " '\"利用日光與自然風乾衣'\"": " '\"與家人/朋友分享慳電小貼士'\"",
        " '\"利用日光与自然风干衣'\"]\"": " '\"与家人/朋友分享悭电小贴士'\"]\""
    }
]